{
  "resourceType": "Patient",
  "id": "Patient-RevisePatient-Example",
  "meta": {
    "profile": [
      "http://hlth.gov.bc.ca/fhir/client/StructureDefinition/bc-patient"
    ]
  },
  "text": {
    "status": "generated",
    "div": "<div xmlns=\"http://www.w3.org/1999/xhtml\"><p><b>John Doe </b> male, DoB: 1940-06-06 ( Account number: 123345654 (OFFICIAL))</p></div>"
  },
  "identifier": [
    {
      "extension": [
        {
          "url": "http://hlth.gov.bc.ca/fhir/client/StructureDefinition/bc-identifier-status-extension",
          "valueCode": "active"
        }
      ],
      "use": "official",
      "type": {
        "coding": [
          {
            "system": "http://terminology.hl7.org/CodeSystem/v2-0203",
            "code": "AN"
          }
        ]
      },
      "system": "http://hlth.gov.bc.ca/fhir/client/id-issuer/SrcCode",
      "value": "123345654",
      "assigner": {
        "display": "ORG_SRC e.g. VPP_CER, IHA_IHA"
      }
    }
  ],
  "name": [
    {
      "use": "usual",
      "family": "Doe",
      "given": [
        "John"
      ]
    }
  ],
  "telecom": [
    {
      "system": "phone",
      "value": "2505554848",
      "use": "home"
    }
  ],
  "gender": "male",
  "birthDate": "1940-06-06",
  "address": [
    {
      "type": "physical",
      "line": [
        "721 FRONT ST"
      ],
      "city": "VICTORIA",
      "state": "BC",
      "postalCode": "V9A3Y3",
      "country": "CA"
    }
  ]
}